Program_Counter.v
module Program_Counter (
                        input clk,
                        input rst_b,
                        output reg [31:0] PC

);

always@(posedge clk)
begin

if(rst_b)
PC <= PC + 4;
else
PC <= 0;

end

endmodule

tb_Program_Counter.v
module tb_Program_Counter ();
reg tb_clk;
reg tb_rst_b;
wire tb_PC;

initial

begin
$dumpfile("Program_Counter.vcd");
$dumpvars();
tb_clk =0;
tb_rst_b =1;

$display("test case 1 ");
#2
tb_rst_b=0;
#5
$display("test Reset time=%0t  ",$time);
if(tb_PC==0)
$display("test is passed");
else
$display("test is failed");

$display("test case 2 ");
#1
tb_rst_b=1'b1;
#9
$display("test Reset time=%0t ,pc %0d ",$time,tb_PC);
if(tb_PC==(tb_PC+4))
$display("test is passed");
else
$display("test is failed");



end    







always #5 tb_clk=~tb_clk;
Program_Counter DUT (
                     .clk(tb_clk),
                     .rst_b(tb_rst_b),
                     .PC(tb_PC)
);


endmodule

Program_Counter.vcd
$date
	Tue Feb 22 20:55:03 2022
$end
$version
	ModelSim Version 10.5b
$end
$timescale
	1ps
$end

$scope module tb_Program_Counter $end
$var reg 1 ! tb_clk $end
$var reg 1 " tb_rst_b $end
$var wire 1 # tb_PC $end

$scope module DUT $end
$var wire 1 $ clk $end
$var wire 1 % rst_b $end
$var reg 32 & PC [31:0] $end
$upscope $end
$upscope $end
$enddefinitions $end
#0
$dumpvars
0!
1"
bx &
x#
1%
0$
$end
#2
0"
0%
#5
1!
1$
b0 &
0#
#8
1"
1%
#10
0!
0$
#15
1!
1$
b100 &
#20
0!
0$
#25
1!
1$
b1000 &
#30
0!
0$
#35
1!
1$
b1100 &
#40
0!
0$
#45
1!
1$
b10000 &
#50
0!
0$
#55
1!
1$
b10100 &
#60
0!
0$
#65
1!
1$
b11000 &
#70
0!
0$
#75
1!
1$
b11100 &
#80
0!
0$
#85
1!
1$
b100000 &
#90
0!
0$
#95
1!
1$
b100100 &
